[
  {
    "ID": 1,
    "Название": "Смартфон Galaxy S21",
    "Описание": "Смартфон с 6.2-дюймовым экраном и тройной камерой.",
    "Цена": 150,
    "Изображение": "https://via.placeholder.com/200?text=Товар+1"
  },
  {
    "ID": 2,
    "Название": "Ноутбук Dell XPS 13",
    "Описание": "Мощный ноутбук с процессором Intel Core i7.",
    "Цена": 300,
    "Изображение": "https://via.placeholder.com/200?text=Товар+2"
  },
  {
    "ID": 3,
    "Название": "Наушники Sony WH-1000XM4",
    "Описание": "Беспроводные наушники с активным шумоподавлением.",
    "Цена": 450,
    "Изображение": "https://via.placeholder.com/200?text=Товар+3"
  },
  {
    "ID": 4,
    "Название": "Планшет Apple iPad Air",
    "Описание": "Планшет с Retina дисплеем и поддержкой Apple Pencil.",
    "Цена": 600,
    "Изображение": "https://via.placeholder.com/200?text=Товар+4"
  },
  {
    "ID": 5,
    "Название": "Камера Canon EOS R5",
    "Описание": "Профессиональная беззеркальная камера с 45 МП.",
    "Цена": 750,
    "Изображение": "https://via.placeholder.com/200?text=Товар+5"
  },
  {
    "ID": 6,
    "Название": "Часы Garmin Fenix 6",
    "Описание": "Спортивные часы с GPS и функцией мониторинга здоровья.",
    "Цена": 900,
    "Изображение": "https://via.placeholder.com/200?text=Товар+6"
  },
  {
    "ID": 7,
    "Название": "Электрическая зубная щетка Oral-B",
    "Описание": "Электрическая зубная щетка с датчиком давления.",
    "Цена": 1050,
    "Изображение": "https://via.placeholder.com/200?text=Товар+7"
  },
  {
    "ID": 8,
    "Название": "Геймпад Xbox Wireless",
    "Описание": "Беспроводной геймпад для консоли Xbox.",
    "Цена": 1200,
    "Изображение": "https://via.placeholder.com/200?text=Товар+8"
  },
  {
    "ID": 9,
    "Название": "Монитор LG UltraWide 29",
    "Описание": "Широкоформатный монитор для продуктивной работы.",
    "Цена": 1350,
    "Изображение": "https://via.placeholder.com/200?text=Товар+9"
  },
  {
    "ID": 10,
    "Название": "Клавиатура Logitech MX Keys",
    "Описание": "Клавиатура с подсветкой и бесшумными клавишами.",
    "Цена": 1000,
    "Изображение": "https://via.placeholder.com/200?text=Товар+10"
  },
  {
    "ID": 11,
    "Название": "Мышь Razer DeathAdder V2",
    "Описание": "Игровая мышь с высокой чувствительностью.",
    "Цена": 1150,
    "Изображение": "https://via.placeholder.com/200?text=Товар+11"
  },
  {
    "ID": 12,
    "Название": "Внешний жесткий диск Seagate",
    "Описание": "Внешний жесткий диск на 1 ТБ для хранения данных.",
    "Цена": 1300,
    "Изображение": "https://via.placeholder.com/200?text=Товар+12"
  },
  {
    "ID": 13,
    "Название": "Умная колонка Amazon Echo",
    "Описание": "Умная колонка с поддержкой Alexa и Bluetooth.",
    "Цена": 1450,
    "Изображение": "https://via.placeholder.com/200?text=Товар+13"
  },
  {
    "ID": 14,
    "Название": "Кофеварка De'Longhi Magnifica",
    "Описание": "Кофеварка с функцией приготовления капучино.",
    "Цена": 1600,
    "Изображение": "https://via.placeholder.com/200?text=Товар+14"
  },
  {
    "ID": 15,
    "Название": "Холодильник Samsung Family Hub",
    "Описание": "Холодильник с сенсорным экраном и Wi-Fi.",
    "Цена": 1750,
    "Изображение": "https://via.placeholder.com/200?text=Товар+15"
  },
  {
    "ID": 16,
    "Название": "Пылесос Dyson V11",
    "Описание": "Беспроводной пылесос с длительным временем работы.",
    "Цена": 1900,
    "Изображение": "https://via.placeholder.com/200?text=Товар+16"
  },
  {
    "ID": 17,
    "Название": "Стиральная машина Bosch Serie 4",
    "Описание": "Стиральная машина с функцией сушения.",
    "Цена": 2050,
    "Изображение": "https://via.placeholder.com/200?text=Товар+17"
  },
  {
    "ID": 18,
    "Название": "Микроволновая печь Panasonic",
    "Описание": "Микроволновая печь с инверторным управлением.",
    "Цена": 2200,
    "Изображение": "https://via.placeholder.com/200?text=Товар+18"
  },
  {
    "ID": 19,
    "Название": "Фитнес-браслет Xiaomi Mi Band 6",
    "Описание": "Фитнес-браслет с мониторингом активности и сна.",
    "Цена": 2350,
    "Изображение": "https://via.placeholder.com/200?text=Товар+19"
  },
  {
    "ID": 20,
    "Название": "Техника для стирки LG TWINWash",
    "Описание": "Умная техника для стирки с двумя барабанами.",
    "Цена": 2000,
    "Изображение": "https://via.placeholder.com/200?text=Товар+20"
  },
  {
    "ID": 21,
    "Название": "Проектор Epson Home Cinema",
    "Описание": "Проектор с высокой яркостью и разрешением Full HD.",
    "Цена": 2150,
    "Изображение": "https://via.placeholder.com/200?text=Товар+21"
  },
  {
    "ID": 22,
    "Название": "Кинотеатр на дому Samsung",
    "Описание": "Кинотеатр на дому с системой объемного звука.",
    "Цена": 2300,
    "Изображение": "https://via.placeholder.com/200?text=Товар+22"
  },
  {
    "ID": 23,
    "Название": "Виртуальная реальность Oculus Quest 2",
    "Описание": "Виртуальные очки для игр и развлечений.",
    "Цена": 2450,
    "Изображение": "https://via.placeholder.com/200?text=Товар+23"
  },
  {
    "ID": 24,
    "Название": "Гироскутер Xiaomi",
    "Описание": "Гироскутер с управлением через приложение.",
    "Цена": 2600,
    "Изображение": "https://via.placeholder.com/200?text=Товар+24"
  },
  {
    "ID": 25,
    "Название": "Электросамокат Ninebot",
    "Описание": "Электросамокат с максимальной скоростью 25 км/ч.",
    "Цена": 2750,
    "Изображение": "https://via.placeholder.com/200?text=Товар+25"
  },
  {
    "ID": 26,
    "Название": "Рюкзак The North Face",
    "Описание": "Удобный рюкзак для путешествий и повседневного использования.",
    "Цена": 2900,
    "Изображение": "https://via.placeholder.com/200?text=Товар+26"
  },
  {
    "ID": 27,
    "Название": "Спортивная обувь Adidas Ultraboost",
    "Описание": "Легкие спортивные кроссовки для бега.",
    "Цена": 3050,
    "Изображение": "https://via.placeholder.com/200?text=Товар+27"
  },
  {
    "ID": 28,
    "Название": "Футболка Nike Dri-FIT",
    "Описание": "Футболка из дышащего материала для тренировок.",
    "Цена": 3200,
    "Изображение": "https://via.placeholder.com/200?text=Товар+28"
  },
  {
    "ID": 29,
    "Название": "Джинсы Levi's 501",
    "Описание": "Классические джинсы с прямым кроем.",
    "Цена": 3350,
    "Изображение": "https://via.placeholder.com/200?text=Товар+29"
  },
  {
    "ID": 30,
    "Название": "Сумка Michael Kors",
    "Описание": "Стильная сумка для документов и ноутбука.",
    "Цена": 3000,
    "Изображение": "https://via.placeholder.com/200?text=Товар+30"
  },
  {
    "ID": 31,
    "Название": "Пальто Calvin Klein",
    "Описание": "Элегантное пальто для холодной погоды.",
    "Цена": 3150,
    "Изображение": "https://via.placeholder.com/200?text=Товар+31"
  },
  {
    "ID": 32,
    "Название": "Шарф Burberry",
    "Описание": "Шарф из натуральной шерсти.",
    "Цена": 3300,
    "Изображение": "https://via.placeholder.com/200?text=Товар+32"
  },
  {
    "ID": 33,
    "Название": "Парфюм Chanel No. 5",
    "Описание": "Популярный парфюм с цветочными нотами.",
    "Цена": 3450,
    "Изображение": "https://via.placeholder.com/200?text=Товар+33"
  },
  {
    "ID": 34,
    "Название": "Косметика L'Oreal",
    "Описание": "Косметика для ухода за кожей с витаминами.",
    "Цена": 3600,
    "Изображение": "https://via.placeholder.com/200?text=Товар+34"
  },
  {
    "ID": 35,
    "Название": "Шампунь Pantene Pro-V",
    "Описание": "Шампунь для нормальных и сухих волос.",
    "Цена": 3750,
    "Изображение": "https://via.placeholder.com/200?text=Товар+35"
  },
  {
    "ID": 36,
    "Название": "Крем для лица Nivea",
    "Описание": "Крем для лица с защитой от солнца.",
    "Цена": 3900,
    "Изображение": "https://via.placeholder.com/200?text=Товар+36"
  },
  {
    "ID": 37,
    "Название": "Зубная паста Sensodyne",
    "Описание": "Зубная паста для чувствительных зубов.",
    "Цена": 4050,
    "Изображение": "https://via.placeholder.com/200?text=Товар+37"
  },
  {
    "ID": 38,
    "Название": "Сыр моцарелла Galbani",
    "Описание": "Сыр моцарелла для пиццы и салатов.",
    "Цена": 4200,
    "Изображение": "https://via.placeholder.com/200?text=Товар+38"
  },
  {
    "ID": 39,
    "Название": "Кофе Lavazza",
    "Описание": "Кофе в зернах с ярким вкусом и ароматом.",
    "Цена": 4350,
    "Изображение": "https://via.placeholder.com/200?text=Товар+39"
  },
  {
    "ID": 40,
    "Название": "Шоколад Milka",
    "Описание": "Шоколад с нежной текстурой.",
    "Цена": 4000,
    "Изображение": "https://via.placeholder.com/200?text=Товар+40"
  },
  {
    "ID": 41,
    "Название": "Чай Lipton",
    "Описание": "Чай с натуральными ароматами.",
    "Цена": 4150,
    "Изображение": "https://via.placeholder.com/200?text=Товар+41"
  },
  {
    "ID": 42,
    "Название": "Орехи Mix Nuts",
    "Описание": "Смесь орехов для закусок.",
    "Цена": 4300,
    "Изображение": "https://via.placeholder.com/200?text=Товар+42"
  },
  {
    "ID": 43,
    "Название": "Сухофрукты Sun-Maid",
    "Описание": "Сухофрукты для здорового перекуса.",
    "Цена": 4450,
    "Изображение": "https://via.placeholder.com/200?text=Товар+43"
  },
  {
    "ID": 44,
    "Название": "Вино Cabernet Sauvignon",
    "Описание": "Вино с ярким вкусом и ароматом.",
    "Цена": 4600,
    "Изображение": "https://via.placeholder.com/200?text=Товар+44"
  },
  {
    "ID": 45,
    "Название": "Пиво Heineken",
    "Описание": "Пиво с легким хмелевым вкусом.",
    "Цена": 4750,
    "Изображение": "https://via.placeholder.com/200?text=Товар+45"
  },
  {
    "ID": 46,
    "Название": "Соки Tropicana",
    "Описание": "Соки из свежих фруктов.",
    "Цена": 4900,
    "Изображение": "https://via.placeholder.com/200?text=Товар+46"
  },
  {
    "ID": 47,
    "Название": "Энергетик Red Bull",
    "Описание": "Энергетик для бодрости и энергии.",
    "Цена": 5050,
    "Изображение": "https://via.placeholder.com/200?text=Товар+47"
  },
  {
    "ID": 48,
    "Название": "Вода San Pellegrino",
    "Описание": "Минеральная вода с газом.",
    "Цена": 5200,
    "Изображение": "https://via.placeholder.com/200?text=Товар+48"
  },
  {
    "ID": 49,
    "Название": "Печенье Oreo",
    "Описание": "Песочное печенье с кремовой начинкой.",
    "Цена": 5350,
    "Изображение": "https://via.placeholder.com/200?text=Товар+49"
  },
  {
    "ID": 50,
    "Название": "Конфеты Kinder",
    "Описание": "Конфеты с шоколадной оболочкой.",
    "Цена": 5000,
    "Изображение": "https://via.placeholder.com/200?text=Товар+50"
  }
]
